rocketx/providers/common/sql/__init__.py
rocketx/providers/common/sql/get_provider_info.py
rocketx/providers/common/sql/hooks/__init__.py
rocketx/providers/common/sql/hooks/handlers.py
rocketx/providers/common/sql/hooks/sql.py
rocketx_providers_common_sql-0.1.2.dist-info/entry_points.txt
rocketx_providers_common_sql-0.1.2.dist-info/WHEEL
rocketx_providers_common_sql-0.1.2.dist-info/METADATA
rocketx_providers_common_sql-0.1.2.dist-info/RECORD
